[
  {
    "author": "impactopdesign",
    "link_thumb": "https://live.staticflickr.com/65535/51670581840_ee2725e1aa_o.gif",
    "link_bin": "https://github.com/lmbstudiocontact/mb6_0/raw/main/405.bin",
    "id_bin": "405",
    "list_language": [],
    "array_tags": [
      "digital",
      "soccer",
      "futebol"
    ],
    "list_album": [
      {
        "id_album": "2433880",
        "link_thumb": "https://live.staticflickr.com/65535/51670581840_ee2725e1aa_o.gif",
        "title": "None"
      }
    ]
  },
  {
    "author": "impactopdesign",
    "link_thumb": "https://live.staticflickr.com/65535/51669945073_a51b6147ae_o.gif",
    "link_bin": "https://github.com/lmbstudiocontact/mb6_0/raw/main/407.bin",
    "id_bin": "407",
    "list_language": [],
    "array_tags": [
      "digital",
      "soccer",
      "futebol"
    ],
    "list_album": [
      {
        "id_album": "2433880",
        "link_thumb": "https://live.staticflickr.com/65535/51669945073_a51b6147ae_o.gif",
        "title": "None"
      }
    ]
  },
  {
    "author": "impactopdesign",
    "link_thumb": "https://live.staticflickr.com/65535/51670591555_efd4b0411a_o.gif",
    "link_bin": "https://github.com/lmbstudiocontact/mb6_0/raw/main/458.bin",
    "id_bin": "458",
    "list_language": [],
    "array_tags": [
      "digital",
      "soccer",
      "brasil",
      "futebol"
    ],
    "list_album": [
      {
        "id_album": "2433880",
        "link_thumb": "https://live.staticflickr.com/65535/51670591555_efd4b0411a_o.gif",
        "title": "None"
      }
    ]
  },
  {
    "author": "impactopdesign",
    "link_thumb": "https://live.staticflickr.com/65535/51669715796_5c8c089111_o.gif",
    "link_bin": "https://github.com/lmbstudiocontact/mb6_0/raw/main/470.bin",
    "id_bin": "470",
    "list_language": [],
    "array_tags": [
      "digital",
      "soccer",
      "futebol"
    ],
    "list_album": [
      {
        "id_album": "2433880",
        "link_thumb": "https://live.staticflickr.com/65535/51669715796_5c8c089111_o.gif",
        "title": "None"
      }
    ]
  },
  {
    "author": "impactopdesign",
    "link_thumb": "https://live.staticflickr.com/65535/51670402799_21fdecf9ba_o.gif",
    "link_bin": "https://github.com/lmbstudiocontact/mb6_0/raw/main/471.bin",
    "id_bin": "471",
    "list_language": [],
    "array_tags": [
      "digital",
      "soccer",
      "futebol"
    ],
    "list_album": [
      {
        "id_album": "2433880",
        "link_thumb": "https://live.staticflickr.com/65535/51670402799_21fdecf9ba_o.gif",
        "title": "None"
      }
    ]
  },
  {
    "author": "impactopdesign",
    "link_thumb": "https://live.staticflickr.com/65535/51669717331_253c41bbf5_o.gif",
    "link_bin": "https://github.com/lmbstudiocontact/mb6_0/raw/main/479.bin",
    "id_bin": "479",
    "list_language": [],
    "array_tags": [
      "digital",
      "soccer",
      "animated",
      "futebol",
      "animation"
    ],
    "list_album": [
      {
        "id_album": "2433880",
        "link_thumb": "https://live.staticflickr.com/65535/51669717331_253c41bbf5_o.gif",
        "title": "None"
      }
    ]
  },
  {
    "author": "demetriusbringel_",
    "link_thumb": "https://live.staticflickr.com/65535/51670619865_784d51fd8f_o.gif",
    "link_bin": "https://github.com/lmbstudiocontact/mb6_0/raw/main/596.bin",
    "id_bin": "596",
    "list_language": [],
    "array_tags": [
      "date",
      "digital",
      "soccer",
      "blue",
      "month",
      "heartrate",
      "weekday",
      "futebol",
      "battery",
      "steps",
      "day"
    ],
    "list_album": [
      {
        "id_album": "2433880",
        "link_thumb": "https://live.staticflickr.com/65535/51670619865_784d51fd8f_o.gif",
        "title": "None"
      }
    ]
  },
  {
    "author": "impactopdesign",
    "link_thumb": "https://live.staticflickr.com/65535/51669813003_57001f4b66_o.gif",
    "link_bin": "https://github.com/lmbstudiocontact/mb6_1/raw/main/1853.bin",
    "id_bin": "1853",
    "list_language": [],
    "array_tags": [
      "digital",
      "pulse",
      "futebol",
      "battery",
      "steps"
    ],
    "list_album": [
      {
        "id_album": "2433880",
        "link_thumb": "https://live.staticflickr.com/65535/51669813003_57001f4b66_o.gif",
        "title": "None"
      }
    ]
  },
  {
    "author": "impactopdesign",
    "link_thumb": "https://live.staticflickr.com/65535/51670259809_44d0afa812_o.gif",
    "link_bin": "https://github.com/lmbstudiocontact/mb6_1/raw/main/1854.bin",
    "id_bin": "1854",
    "list_language": [],
    "array_tags": [
      "analog",
      "futebol"
    ],
    "list_album": [
      {
        "id_album": "2433880",
        "link_thumb": "https://live.staticflickr.com/65535/51670259809_44d0afa812_o.gif",
        "title": "None"
      }
    ]
  },
  {
    "author": "impactopdesign",
    "link_thumb": "https://live.staticflickr.com/65535/51669813463_a230eed570_o.gif",
    "link_bin": "https://github.com/lmbstudiocontact/mb6_1/raw/main/1855.bin",
    "id_bin": "1855",
    "list_language": [],
    "array_tags": [
      "digital",
      "futebol"
    ],
    "list_album": [
      {
        "id_album": "2433880",
        "link_thumb": "https://live.staticflickr.com/65535/51669813463_a230eed570_o.gif",
        "title": "None"
      }
    ]
  },
  {
    "author": "demetriusbringel_",
    "link_thumb": "https://live.staticflickr.com/65535/51670329549_d0af019dba_o.gif",
    "link_bin": "https://github.com/lmbstudiocontact/mb6_1/raw/main/2311.bin",
    "id_bin": "2311",
    "list_language": [],
    "array_tags": [
      "digital",
      "date",
      "soccer",
      "heartrate",
      "brasil",
      "futebol",
      "battery",
      "steps",
      "day"
    ],
    "list_album": [
      {
        "id_album": "2433880",
        "link_thumb": "https://live.staticflickr.com/65535/51670329549_d0af019dba_o.gif",
        "title": "None"
      }
    ]
  },
  {
    "author": "demetriusbringel_",
    "link_thumb": "https://live.staticflickr.com/65535/51670522495_fb2fd0f15f_o.gif",
    "link_bin": "https://github.com/lmbstudiocontact/mb6_1/raw/main/2317.bin",
    "id_bin": "2317",
    "list_language": [],
    "array_tags": [
      "digital",
      "date",
      "soccer",
      "seconds",
      "heartrate",
      "brasil",
      "futebol",
      "battery",
      "steps"
    ],
    "list_album": [
      {
        "id_album": "2433880",
        "link_thumb": "https://live.staticflickr.com/65535/51670522495_fb2fd0f15f_o.gif",
        "title": "None"
      }
    ]
  },
  {
    "author": "demetriusbringel_",
    "link_thumb": "https://live.staticflickr.com/65535/51670330904_95831db4c5_o.gif",
    "link_bin": "https://github.com/lmbstudiocontact/mb6_1/raw/main/2318.bin",
    "id_bin": "2318",
    "list_language": [],
    "array_tags": [
      "digital",
      "date",
      "soccer",
      "heartrate",
      "brasil",
      "futebol",
      "battery",
      "sport",
      "steps"
    ],
    "list_album": [
      {
        "id_album": "2433880",
        "link_thumb": "https://live.staticflickr.com/65535/51670330904_95831db4c5_o.gif",
        "title": "None"
      }
    ]
  }
]