[
  {
    "author": "magnim",
    "link_thumb": "https://live.staticflickr.com/65535/51670395934_9b5612d5f8_o.gif",
    "link_bin": "https://github.com/lmbstudiocontact/mb6_0/raw/main/442.bin",
    "id_bin": "442",
    "list_language": [],
    "array_tags": [
      "digital",
      "kcal",
      "distance",
      "weather",
      "pulse",
      "italian",
      "turquoise",
      "steps"
    ],
    "list_album": [
      {
        "id_album": "2433880",
        "link_thumb": "https://live.staticflickr.com/65535/51670395934_9b5612d5f8_o.gif",
        "title": "None"
      }
    ]
  }
]