[
  {
    "author": "CTEPE0",
    "link_thumb": "https://live.staticflickr.com/65535/51669709518_5a3f674d6e_o.gif",
    "link_bin": "https://github.com/lmbstudiocontact/mb6_0/raw/main/1080.bin",
    "id_bin": "1080",
    "list_language": [],
    "array_tags": [
      "dj",
      "google",
      "dance",
      "animation"
    ],
    "list_album": [
      {
        "id_album": "2433880",
        "link_thumb": "https://live.staticflickr.com/65535/51669709518_5a3f674d6e_o.gif",
        "title": "None"
      }
    ]
  },
  {
    "author": "Chclt",
    "link_thumb": "https://live.staticflickr.com/65535/51670155889_4834f4a7ba_o.gif",
    "link_bin": "https://github.com/lmbstudiocontact/mb6_0/raw/main/1081.bin",
    "id_bin": "1081",
    "list_language": [],
    "array_tags": [
      "date",
      "weather",
      "google",
      "battery",
      "pixel",
      "sport",
      "steps"
    ],
    "list_album": [
      {
        "id_album": "2211858",
        "link_thumb": "https://live.staticflickr.com/65535/51670155889_4834f4a7ba_o.gif",
        "title": "Game"
      }
    ]
  },
  {
    "author": "neux",
    "link_thumb": "https://live.staticflickr.com/65535/51669529466_e7772a8e1b_o.gif",
    "link_bin": "https://github.com/lmbstudiocontact/mb6_0/raw/main/1605.bin",
    "id_bin": "1605",
    "list_language": [],
    "array_tags": [
      "date",
      "cat",
      "black",
      "weather",
      "google",
      "battery",
      "sport",
      "steps",
      "pixel"
    ],
    "list_album": [
      {
        "id_album": "2433880",
        "link_thumb": "https://live.staticflickr.com/65535/51669529466_e7772a8e1b_o.gif",
        "title": "None"
      }
    ]
  },
  {
    "author": "NEORUAA",
    "link_thumb": "https://live.staticflickr.com/65535/51669762991_dd5bebd283_o.gif",
    "link_bin": "https://github.com/lmbstudiocontact/mb6_0/raw/main/7.bin",
    "id_bin": "7",
    "list_language": [],
    "array_tags": [
      "digital",
      "analog",
      "google",
      "battery"
    ],
    "list_album": [
      {
        "id_album": "2433880",
        "link_thumb": "https://live.staticflickr.com/65535/51669762991_dd5bebd283_o.gif",
        "title": "None"
      }
    ]
  },
  {
    "author": "neux",
    "link_thumb": "https://live.staticflickr.com/65535/51670487215_450a57f8b9_o.gif",
    "link_bin": "https://github.com/lmbstudiocontact/mb6_1/raw/main/2103.bin",
    "id_bin": "2103",
    "list_language": [],
    "array_tags": [
      "date",
      "xxxtentacion",
      "bluetooth",
      "weather",
      "google",
      "simple",
      "time",
      "dnd",
      "battery",
      "heart"
    ],
    "list_album": [
      {
        "id_album": "2433880",
        "link_thumb": "https://live.staticflickr.com/65535/51670487215_450a57f8b9_o.gif",
        "title": "None"
      }
    ]
  },
  {
    "author": "johny_tran",
    "link_thumb": "https://live.staticflickr.com/65535/51670307439_e6d99833e1_o.gif",
    "link_bin": "https://github.com/lmbstudiocontact/mb6_1/raw/main/2183.bin",
    "id_bin": "2183",
    "list_language": [],
    "array_tags": [
      "apple",
      "google",
      "macos"
    ],
    "list_album": [
      {
        "id_album": "2433880",
        "link_thumb": "https://live.staticflickr.com/65535/51670307439_e6d99833e1_o.gif",
        "title": "None"
      }
    ]
  }
]