[
  {
    "author": "ZanarkTempest",
    "link_thumb": "https://live.staticflickr.com/65535/51668817847_3b91a1e3ac_o.gif",
    "link_bin": "https://github.com/lmbstudiocontact/mb6_1/raw/main/2146.bin",
    "id_bin": "2146",
    "list_language": [],
    "array_tags": [
      "heartrate",
      "anime"
    ],
    "list_album": [
      {
        "id_album": "-2075887794",
        "link_thumb": "https://live.staticflickr.com/65535/51668817847_3b91a1e3ac_o.gif",
        "title": "Cartoon"
      }
    ]
  },
  {
    "author": "ZanarkTempest",
    "link_thumb": "https://live.staticflickr.com/65535/51669857163_b28c260af1_o.gif",
    "link_bin": "https://github.com/lmbstudiocontact/mb6_1/raw/main/2147.bin",
    "id_bin": "2147",
    "list_language": [],
    "array_tags": [
      "naruto",
      "heartrate",
      "sasori",
      "anime"
    ],
    "list_album": [
      {
        "id_album": "63410260",
        "link_thumb": "https://live.staticflickr.com/65535/51669857163_b28c260af1_o.gif",
        "title": "Anime"
      }
    ]
  },
  {
    "author": "ZanarkTempest",
    "link_thumb": "https://live.staticflickr.com/65535/51670303474_890e795456_o.gif",
    "link_bin": "https://github.com/lmbstudiocontact/mb6_1/raw/main/2148.bin",
    "id_bin": "2148",
    "list_language": [],
    "array_tags": [
      "sasuke",
      "naruto",
      "heartrate",
      "anime"
    ],
    "list_album": [
      {
        "id_album": "63410260",
        "link_thumb": "https://live.staticflickr.com/65535/51670303474_890e795456_o.gif",
        "title": "Anime"
      }
    ]
  },
  {
    "author": "ZanarkTempest",
    "link_thumb": "https://live.staticflickr.com/65535/51668818462_9eba4bb42a_o.gif",
    "link_bin": "https://github.com/lmbstudiocontact/mb6_1/raw/main/2149.bin",
    "id_bin": "2149",
    "list_language": [],
    "array_tags": [
      "sasuke",
      "naruto",
      "heartrate",
      "anime"
    ],
    "list_album": [
      {
        "id_album": "63410260",
        "link_thumb": "https://live.staticflickr.com/65535/51668818462_9eba4bb42a_o.gif",
        "title": "Anime"
      }
    ]
  },
  {
    "author": "ZanarkTempest",
    "link_thumb": "https://live.staticflickr.com/65535/51669616706_16cf3394fe_o.gif",
    "link_bin": "https://github.com/lmbstudiocontact/mb6_1/raw/main/2150.bin",
    "id_bin": "2150",
    "list_language": [],
    "array_tags": [
      "naruto",
      "tobi",
      "heartrate",
      "anime"
    ],
    "list_album": [
      {
        "id_album": "63410260",
        "link_thumb": "https://live.staticflickr.com/65535/51669616706_16cf3394fe_o.gif",
        "title": "Anime"
      }
    ]
  },
  {
    "author": "ZanarkTempest",
    "link_thumb": "https://live.staticflickr.com/65535/51669858113_cdc2ecf42b_o.gif",
    "link_bin": "https://github.com/lmbstudiocontact/mb6_1/raw/main/2151.bin",
    "id_bin": "2151",
    "list_language": [],
    "array_tags": [
      "yamato",
      "heartrate",
      "anime"
    ],
    "list_album": [
      {
        "id_album": "63410260",
        "link_thumb": "https://live.staticflickr.com/65535/51669858113_cdc2ecf42b_o.gif",
        "title": "Anime"
      }
    ]
  },
  {
    "author": "ZanarkTempest",
    "link_thumb": "https://live.staticflickr.com/65535/51670304479_7235cbc29f_o.gif",
    "link_bin": "https://github.com/lmbstudiocontact/mb6_1/raw/main/2152.bin",
    "id_bin": "2152",
    "list_language": [],
    "array_tags": [
      "yamato",
      "heartrate",
      "anime"
    ],
    "list_album": [
      {
        "id_album": "63410260",
        "link_thumb": "https://live.staticflickr.com/65535/51670304479_7235cbc29f_o.gif",
        "title": "Anime"
      }
    ]
  },
  {
    "author": "ZanarkTempest",
    "link_thumb": "https://live.staticflickr.com/65535/51670496280_c03a5e8c92_o.gif",
    "link_bin": "https://github.com/lmbstudiocontact/mb6_1/raw/main/2153.bin",
    "id_bin": "2153",
    "list_language": [],
    "array_tags": [
      "yamato",
      "heartrate",
      "anime"
    ],
    "list_album": [
      {
        "id_album": "63410260",
        "link_thumb": "https://live.staticflickr.com/65535/51670496280_c03a5e8c92_o.gif",
        "title": "Anime"
      }
    ]
  },
  {
    "author": "ZanarkTempest",
    "link_thumb": "https://live.staticflickr.com/65535/51669858633_6c24c75149_o.gif",
    "link_bin": "https://github.com/lmbstudiocontact/mb6_1/raw/main/2154.bin",
    "id_bin": "2154",
    "list_language": [],
    "array_tags": [
      "yamato",
      "heartrate",
      "anime"
    ],
    "list_album": [
      {
        "id_album": "63410260",
        "link_thumb": "https://live.staticflickr.com/65535/51669858633_6c24c75149_o.gif",
        "title": "Anime"
      }
    ]
  },
  {
    "author": "ZanarkTempest",
    "link_thumb": "https://live.staticflickr.com/65535/51669617591_cc3363db49_o.gif",
    "link_bin": "https://github.com/lmbstudiocontact/mb6_1/raw/main/2155.bin",
    "id_bin": "2155",
    "list_language": [],
    "array_tags": [
      "heartrate",
      "hawk",
      "anime"
    ],
    "list_album": [
      {
        "id_album": "63410260",
        "link_thumb": "https://live.staticflickr.com/65535/51669617591_cc3363db49_o.gif",
        "title": "Anime"
      }
    ]
  },
  {
    "author": "ZanarkTempest",
    "link_thumb": "https://live.staticflickr.com/65535/51670496965_cb8cb800c0_o.gif",
    "link_bin": "https://github.com/lmbstudiocontact/mb6_1/raw/main/2158.bin",
    "id_bin": "2158",
    "list_language": [],
    "array_tags": [
      "heartrate",
      "hamtaro",
      "anime"
    ],
    "list_album": [
      {
        "id_album": "2433880",
        "link_thumb": "https://live.staticflickr.com/65535/51670496965_cb8cb800c0_o.gif",
        "title": "None"
      }
    ]
  },
  {
    "author": "ZanarkTempest",
    "link_thumb": "https://live.staticflickr.com/65535/51669859348_e420a97c76_o.gif",
    "link_bin": "https://github.com/lmbstudiocontact/mb6_1/raw/main/2159.bin",
    "id_bin": "2159",
    "list_language": [],
    "array_tags": [
      "heartrate",
      "himeno",
      "anime"
    ],
    "list_album": [
      {
        "id_album": "63410260",
        "link_thumb": "https://live.staticflickr.com/65535/51669859348_e420a97c76_o.gif",
        "title": "Anime"
      }
    ]
  },
  {
    "author": "ZanarkTempest",
    "link_thumb": "https://live.staticflickr.com/65535/51669859748_0804ea293b_o.gif",
    "link_bin": "https://github.com/lmbstudiocontact/mb6_1/raw/main/2161.bin",
    "id_bin": "2161",
    "list_language": [],
    "array_tags": [
      "heartrate",
      "reze",
      "anime"
    ],
    "list_album": [
      {
        "id_album": "63410260",
        "link_thumb": "https://live.staticflickr.com/65535/51669859748_0804ea293b_o.gif",
        "title": "Anime"
      }
    ]
  },
  {
    "author": "ZanarkTempest",
    "link_thumb": "https://live.staticflickr.com/65535/51669620156_3c75063919_o.gif",
    "link_bin": "https://github.com/lmbstudiocontact/mb6_1/raw/main/2186.bin",
    "id_bin": "2186",
    "list_language": [],
    "array_tags": [
      "heartrate",
      "steinsgate",
      "steps",
      "anime"
    ],
    "list_album": [
      {
        "id_album": "63410260",
        "link_thumb": "https://live.staticflickr.com/65535/51669620156_3c75063919_o.gif",
        "title": "Anime"
      }
    ]
  },
  {
    "author": "ZanarkTempest",
    "link_thumb": "https://live.staticflickr.com/65535/51670309354_4b58fb9b2e_o.gif",
    "link_bin": "https://github.com/lmbstudiocontact/mb6_1/raw/main/2197.bin",
    "id_bin": "2197",
    "list_language": [],
    "array_tags": [
      "heartrate",
      "steps",
      "anime"
    ],
    "list_album": [
      {
        "id_album": "63410260",
        "link_thumb": "https://live.staticflickr.com/65535/51670309354_4b58fb9b2e_o.gif",
        "title": "Anime"
      }
    ]
  },
  {
    "author": "ZanarkTempest",
    "link_thumb": "https://live.staticflickr.com/65535/51669864428_460795af58_o.gif",
    "link_bin": "https://github.com/lmbstudiocontact/mb6_1/raw/main/2203.bin",
    "id_bin": "2203",
    "list_language": [],
    "array_tags": [
      "pokemon",
      "heartrate",
      "steps",
      "lugia",
      "anime"
    ],
    "list_album": [
      {
        "id_album": "63410260",
        "link_thumb": "https://live.staticflickr.com/65535/51669864428_460795af58_o.gif",
        "title": "Anime"
      }
    ]
  },
  {
    "author": "ZanarkTempest",
    "link_thumb": "https://live.staticflickr.com/65535/51669623591_d5d372e064_o.gif",
    "link_bin": "https://github.com/lmbstudiocontact/mb6_1/raw/main/2205.bin",
    "id_bin": "2205",
    "list_language": [],
    "array_tags": [
      "pokemon",
      "heartrate",
      "games",
      "charizard",
      "steps",
      "anime"
    ],
    "list_album": [
      {
        "id_album": "63410260",
        "link_thumb": "https://live.staticflickr.com/65535/51669623591_d5d372e064_o.gif",
        "title": "Anime"
      }
    ]
  },
  {
    "author": "ZanarkTempest",
    "link_thumb": "https://live.staticflickr.com/65535/51669623856_a3a4cd2ea6_o.gif",
    "link_bin": "https://github.com/lmbstudiocontact/mb6_1/raw/main/2206.bin",
    "id_bin": "2206",
    "list_language": [],
    "array_tags": [
      "pokemon",
      "blastoise",
      "heartrate",
      "games",
      "steps",
      "anime"
    ],
    "list_album": [
      {
        "id_album": "63410260",
        "link_thumb": "https://live.staticflickr.com/65535/51669623856_a3a4cd2ea6_o.gif",
        "title": "Anime"
      }
    ]
  },
  {
    "author": "ZanarkTempest",
    "link_thumb": "https://live.staticflickr.com/65535/51669865373_1773ea4abc_o.gif",
    "link_bin": "https://github.com/lmbstudiocontact/mb6_1/raw/main/2207.bin",
    "id_bin": "2207",
    "list_language": [],
    "array_tags": [
      "pokemon",
      "heartrate",
      "games",
      "venusaur",
      "steps",
      "anime"
    ],
    "list_album": [
      {
        "id_album": "63410260",
        "link_thumb": "https://live.staticflickr.com/65535/51669865373_1773ea4abc_o.gif",
        "title": "Anime"
      }
    ]
  },
  {
    "author": "ZanarkTempest",
    "link_thumb": "https://live.staticflickr.com/65535/51670311734_a4d475fd90_o.gif",
    "link_bin": "https://github.com/lmbstudiocontact/mb6_1/raw/main/2214.bin",
    "id_bin": "2214",
    "list_language": [],
    "array_tags": [
      "kobeni",
      "heartrate",
      "steps",
      "anime"
    ],
    "list_album": [
      {
        "id_album": "63410260",
        "link_thumb": "https://live.staticflickr.com/65535/51670311734_a4d475fd90_o.gif",
        "title": "Anime"
      }
    ]
  },
  {
    "author": "ZanarkTempest",
    "link_thumb": "https://live.staticflickr.com/65535/51669867148_944a74805c_o.gif",
    "link_bin": "https://github.com/lmbstudiocontact/mb6_1/raw/main/2227.bin",
    "id_bin": "2227",
    "list_language": [],
    "array_tags": [
      "heartrate",
      "steps",
      "anime"
    ],
    "list_album": [
      {
        "id_album": "63410260",
        "link_thumb": "https://live.staticflickr.com/65535/51669867148_944a74805c_o.gif",
        "title": "Anime"
      }
    ]
  },
  {
    "author": "jpcreator",
    "link_thumb": "https://live.staticflickr.com/65535/51669627346_b15674a130_o.gif",
    "link_bin": "https://github.com/lmbstudiocontact/mb6_1/raw/main/2239.bin",
    "id_bin": "2239",
    "list_language": [],
    "array_tags": [
      "digital",
      "date",
      "heartrate",
      "weekday",
      "uvi",
      "battery",
      "steps",
      "animation",
      "donotdisturb",
      "bluetooth",
      "weather",
      "pai",
      "lock",
      "anime"
    ],
    "list_album": [
      {
        "id_album": "2433880",
        "link_thumb": "https://live.staticflickr.com/65535/51669627346_b15674a130_o.gif",
        "title": "None"
      }
    ]
  },
  {
    "author": "nutchakrit",
    "link_thumb": "https://live.staticflickr.com/65535/51670506730_582f7b9e68_o.gif",
    "link_bin": "https://github.com/lmbstudiocontact/mb6_1/raw/main/2240.bin",
    "id_bin": "2240",
    "list_language": [],
    "array_tags": [
      "touhou",
      "reimu",
      "hakurei",
      "anime"
    ],
    "list_album": [
      {
        "id_album": "63410260",
        "link_thumb": "https://live.staticflickr.com/65535/51670506730_582f7b9e68_o.gif",
        "title": "Anime"
      }
    ]
  },
  {
    "author": "nutchakrit",
    "link_thumb": "https://live.staticflickr.com/65535/51669627826_9c046c2a48_o.gif",
    "link_bin": "https://github.com/lmbstudiocontact/mb6_1/raw/main/2242.bin",
    "id_bin": "2242",
    "list_language": [],
    "array_tags": [
      "touhou",
      "marisa",
      "kirisame",
      "anime"
    ],
    "list_album": [
      {
        "id_album": "63410260",
        "link_thumb": "https://live.staticflickr.com/65535/51669627826_9c046c2a48_o.gif",
        "title": "Anime"
      }
    ]
  },
  {
    "author": "nutchakrit",
    "link_thumb": "https://live.staticflickr.com/65535/51669628131_5f103463a9_o.gif",
    "link_bin": "https://github.com/lmbstudiocontact/mb6_1/raw/main/2245.bin",
    "id_bin": "2245",
    "list_language": [],
    "array_tags": [
      "touhou",
      "patchouli",
      "anime",
      "knowledge"
    ],
    "list_album": [
      {
        "id_album": "63410260",
        "link_thumb": "https://live.staticflickr.com/65535/51669628131_5f103463a9_o.gif",
        "title": "Anime"
      }
    ]
  },
  {
    "author": "ZanarkTempest",
    "link_thumb": "https://live.staticflickr.com/65535/51669874213_39b639e2ba_o.gif",
    "link_bin": "https://github.com/lmbstudiocontact/mb6_1/raw/main/2270.bin",
    "id_bin": "2270",
    "list_language": [],
    "array_tags": [
      "evangelion",
      "asuka",
      "heartrate",
      "steps",
      "anime"
    ],
    "list_album": [
      {
        "id_album": "63410260",
        "link_thumb": "https://live.staticflickr.com/65535/51669874213_39b639e2ba_o.gif",
        "title": "Anime"
      }
    ]
  },
  {
    "author": "ZanarkTempest",
    "link_thumb": "https://live.staticflickr.com/65535/51669632946_cca8d270bf_o.gif",
    "link_bin": "https://github.com/lmbstudiocontact/mb6_1/raw/main/2271.bin",
    "id_bin": "2271",
    "list_language": [],
    "array_tags": [
      "heartrate",
      "bleach",
      "games",
      "steps",
      "anime"
    ],
    "list_album": [
      {
        "id_album": "63410260",
        "link_thumb": "https://live.staticflickr.com/65535/51669632946_cca8d270bf_o.gif",
        "title": "Anime"
      }
    ]
  },
  {
    "author": "ZanarkTempest",
    "link_thumb": "https://live.staticflickr.com/65535/51669875013_b74cc65018_o.gif",
    "link_bin": "https://github.com/lmbstudiocontact/mb6_1/raw/main/2273.bin",
    "id_bin": "2273",
    "list_language": [],
    "array_tags": [
      "heartrate",
      "games",
      "steps",
      "anime"
    ],
    "list_album": [
      {
        "id_album": "63410260",
        "link_thumb": "https://live.staticflickr.com/65535/51669875013_b74cc65018_o.gif",
        "title": "Anime"
      }
    ]
  },
  {
    "author": "ZanarkTempest",
    "link_thumb": "https://live.staticflickr.com/65535/51670321599_7dd0172abc_o.gif",
    "link_bin": "https://github.com/lmbstudiocontact/mb6_1/raw/main/2277.bin",
    "id_bin": "2277",
    "list_language": [],
    "array_tags": [
      "heartrate",
      "bleach",
      "games",
      "steps",
      "anime"
    ],
    "list_album": [
      {
        "id_album": "63410260",
        "link_thumb": "https://live.staticflickr.com/65535/51670321599_7dd0172abc_o.gif",
        "title": "Anime"
      }
    ]
  },
  {
    "author": "ZanarkTempest",
    "link_thumb": "https://live.staticflickr.com/65535/51668836952_c3b7754d62_o.gif",
    "link_bin": "https://github.com/lmbstudiocontact/mb6_1/raw/main/2278.bin",
    "id_bin": "2278",
    "list_language": [],
    "array_tags": [
      "heartrate",
      "steps",
      "anime"
    ],
    "list_album": [
      {
        "id_album": "63410260",
        "link_thumb": "https://live.staticflickr.com/65535/51668836952_c3b7754d62_o.gif",
        "title": "Anime"
      }
    ]
  },
  {
    "author": "ZanarkTempest",
    "link_thumb": "https://live.staticflickr.com/65535/51670513935_348913f0dd_o.gif",
    "link_bin": "https://github.com/lmbstudiocontact/mb6_1/raw/main/2279.bin",
    "id_bin": "2279",
    "list_language": [],
    "array_tags": [
      "heartrate",
      "hunterxhunter",
      "steps",
      "anime"
    ],
    "list_album": [
      {
        "id_album": "63410260",
        "link_thumb": "https://live.staticflickr.com/65535/51670513935_348913f0dd_o.gif",
        "title": "Anime"
      }
    ]
  },
  {
    "author": "ZanarkTempest",
    "link_thumb": "https://live.staticflickr.com/65535/51669635101_c80b92da79_o.gif",
    "link_bin": "https://github.com/lmbstudiocontact/mb6_1/raw/main/2280.bin",
    "id_bin": "2280",
    "list_language": [],
    "array_tags": [
      "heartrate",
      "hunterxhunter",
      "steps",
      "anime"
    ],
    "list_album": [
      {
        "id_album": "63410260",
        "link_thumb": "https://live.staticflickr.com/65535/51669635101_c80b92da79_o.gif",
        "title": "Anime"
      }
    ]
  },
  {
    "author": "ZanarkTempest",
    "link_thumb": "https://live.staticflickr.com/65535/51670514960_c47eafd8a3_o.gif",
    "link_bin": "https://github.com/lmbstudiocontact/mb6_1/raw/main/2283.bin",
    "id_bin": "2283",
    "list_language": [],
    "array_tags": [
      "heartrate",
      "bleach",
      "steps",
      "anime"
    ],
    "list_album": [
      {
        "id_album": "63410260",
        "link_thumb": "https://live.staticflickr.com/65535/51670514960_c47eafd8a3_o.gif",
        "title": "Anime"
      }
    ]
  },
  {
    "author": "ZanarkTempest",
    "link_thumb": "https://live.staticflickr.com/65535/51669877543_0f58ba1990_o.gif",
    "link_bin": "https://github.com/lmbstudiocontact/mb6_1/raw/main/2284.bin",
    "id_bin": "2284",
    "list_language": [],
    "array_tags": [
      "heartrate",
      "bleach",
      "steps",
      "anime"
    ],
    "list_album": [
      {
        "id_album": "63410260",
        "link_thumb": "https://live.staticflickr.com/65535/51669877543_0f58ba1990_o.gif",
        "title": "Anime"
      }
    ]
  },
  {
    "author": "ZanarkTempest",
    "link_thumb": "https://live.staticflickr.com/65535/51669877788_dedf798cce_o.gif",
    "link_bin": "https://github.com/lmbstudiocontact/mb6_1/raw/main/2285.bin",
    "id_bin": "2285",
    "list_language": [],
    "array_tags": [
      "heartrate",
      "steps",
      "hunterxhunter",
      "anime"
    ],
    "list_album": [
      {
        "id_album": "63410260",
        "link_thumb": "https://live.staticflickr.com/65535/51669877788_dedf798cce_o.gif",
        "title": "Anime"
      }
    ]
  },
  {
    "author": "ZanarkTempest",
    "link_thumb": "https://live.staticflickr.com/65535/51669637421_d646906850_o.gif",
    "link_bin": "https://github.com/lmbstudiocontact/mb6_1/raw/main/2288.bin",
    "id_bin": "2288",
    "list_language": [],
    "array_tags": [
      "heartrate",
      "hunterxhunter",
      "steps",
      "anime"
    ],
    "list_album": [
      {
        "id_album": "63410260",
        "link_thumb": "https://live.staticflickr.com/65535/51669637421_d646906850_o.gif",
        "title": "Anime"
      }
    ]
  },
  {
    "author": "ZanarkTempest",
    "link_thumb": "https://live.staticflickr.com/65535/51670324319_0cf3128942_o.gif",
    "link_bin": "https://github.com/lmbstudiocontact/mb6_1/raw/main/2289.bin",
    "id_bin": "2289",
    "list_language": [],
    "array_tags": [
      "heartrate",
      "hunterxhunter",
      "steps",
      "anime"
    ],
    "list_album": [
      {
        "id_album": "63410260",
        "link_thumb": "https://live.staticflickr.com/65535/51670324319_0cf3128942_o.gif",
        "title": "Anime"
      }
    ]
  },
  {
    "author": "ZanarkTempest",
    "link_thumb": "https://live.staticflickr.com/65535/51670325644_4918d7df9e_o.gif",
    "link_bin": "https://github.com/lmbstudiocontact/mb6_1/raw/main/2293.bin",
    "id_bin": "2293",
    "list_language": [],
    "array_tags": [
      "heartrate",
      "games",
      "steps",
      "anime"
    ],
    "list_album": [
      {
        "id_album": "63410260",
        "link_thumb": "https://live.staticflickr.com/65535/51670325644_4918d7df9e_o.gif",
        "title": "Anime"
      }
    ]
  },
  {
    "author": "ZanarkTempest",
    "link_thumb": "https://live.staticflickr.com/65535/51670325799_638a2c3849_o.gif",
    "link_bin": "https://github.com/lmbstudiocontact/mb6_1/raw/main/2294.bin",
    "id_bin": "2294",
    "list_language": [],
    "array_tags": [
      "heartrate",
      "steps",
      "anime",
      "onepunchman"
    ],
    "list_album": [
      {
        "id_album": "63410260",
        "link_thumb": "https://live.staticflickr.com/65535/51670325799_638a2c3849_o.gif",
        "title": "Anime"
      }
    ]
  },
  {
    "author": "ZanarkTempest",
    "link_thumb": "https://live.staticflickr.com/65535/51669880448_99405fa3cf_o.gif",
    "link_bin": "https://github.com/lmbstudiocontact/mb6_1/raw/main/2296.bin",
    "id_bin": "2296",
    "list_language": [],
    "array_tags": [
      "heartrate",
      "steps",
      "anime",
      "onepunchman"
    ],
    "list_album": [
      {
        "id_album": "63410260",
        "link_thumb": "https://live.staticflickr.com/65535/51669880448_99405fa3cf_o.gif",
        "title": "Anime"
      }
    ]
  },
  {
    "author": "ZanarkTempest",
    "link_thumb": "https://live.staticflickr.com/65535/51669639391_abfe673746_o.gif",
    "link_bin": "https://github.com/lmbstudiocontact/mb6_1/raw/main/2297.bin",
    "id_bin": "2297",
    "list_language": [],
    "array_tags": [
      "heartrate",
      "games",
      "steps",
      "anime"
    ],
    "list_album": [
      {
        "id_album": "63410260",
        "link_thumb": "https://live.staticflickr.com/65535/51669639391_abfe673746_o.gif",
        "title": "Anime"
      }
    ]
  },
  {
    "author": "ZanarkTempest",
    "link_thumb": "https://live.staticflickr.com/65535/51670326899_bbeb7af6c2_o.gif",
    "link_bin": "https://github.com/lmbstudiocontact/mb6_1/raw/main/2299.bin",
    "id_bin": "2299",
    "list_language": [],
    "array_tags": [
      "heartrate",
      "bleach",
      "games",
      "steps",
      "anime"
    ],
    "list_album": [
      {
        "id_album": "63410260",
        "link_thumb": "https://live.staticflickr.com/65535/51670326899_bbeb7af6c2_o.gif",
        "title": "Anime"
      }
    ]
  },
  {
    "author": "ZanarkTempest",
    "link_thumb": "https://live.staticflickr.com/65535/51670328134_bed99db9e4_o.gif",
    "link_bin": "https://github.com/lmbstudiocontact/mb6_1/raw/main/2302.bin",
    "id_bin": "2302",
    "list_language": [],
    "array_tags": [
      "heartrate",
      "games",
      "steps",
      "anime"
    ],
    "list_album": [
      {
        "id_album": "2211858",
        "link_thumb": "https://live.staticflickr.com/65535/51670328134_bed99db9e4_o.gif",
        "title": "Game"
      }
    ]
  },
  {
    "author": "ZanarkTempest",
    "link_thumb": "https://live.staticflickr.com/65535/51670328524_c7cf180395_o.gif",
    "link_bin": "https://github.com/lmbstudiocontact/mb6_1/raw/main/2304.bin",
    "id_bin": "2304",
    "list_language": [],
    "array_tags": [
      "heartrate",
      "hunterxhunter",
      "steps",
      "anime"
    ],
    "list_album": [
      {
        "id_album": "63410260",
        "link_thumb": "https://live.staticflickr.com/65535/51670328524_c7cf180395_o.gif",
        "title": "Anime"
      }
    ]
  },
  {
    "author": "ZanarkTempest",
    "link_thumb": "https://live.staticflickr.com/65535/51669883278_97c805c41d_o.gif",
    "link_bin": "https://github.com/lmbstudiocontact/mb6_1/raw/main/2307.bin",
    "id_bin": "2307",
    "list_language": [],
    "array_tags": [
      "heartrate",
      "luffy",
      "animated",
      "onepiece",
      "steps",
      "anime",
      "animation"
    ],
    "list_album": [
      {
        "id_album": "63410260",
        "link_thumb": "https://live.staticflickr.com/65535/51669883278_97c805c41d_o.gif",
        "title": "Anime"
      }
    ]
  },
  {
    "author": "ZanarkTempest",
    "link_thumb": "https://live.staticflickr.com/65535/51668844422_a409d14e47_o.gif",
    "link_bin": "https://github.com/lmbstudiocontact/mb6_1/raw/main/2308.bin",
    "id_bin": "2308",
    "list_language": [],
    "array_tags": [
      "heartrate",
      "luffy",
      "animated",
      "onepiece",
      "steps",
      "anime",
      "animation"
    ],
    "list_album": [
      {
        "id_album": "63410260",
        "link_thumb": "https://live.staticflickr.com/65535/51668844422_a409d14e47_o.gif",
        "title": "Anime"
      }
    ]
  },
  {
    "author": "nutchakrit",
    "link_thumb": "https://live.staticflickr.com/65535/51669650536_5893de6501_o.gif",
    "link_bin": "https://github.com/lmbstudiocontact/mb6_1/raw/main/2356.bin",
    "id_bin": "2356",
    "list_language": [],
    "array_tags": [
      "game",
      "anime"
    ],
    "list_album": [
      {
        "id_album": "63410260",
        "link_thumb": "https://live.staticflickr.com/65535/51669650536_5893de6501_o.gif",
        "title": "Anime"
      }
    ]
  },
  {
    "author": "nutchakrit",
    "link_thumb": "https://live.staticflickr.com/65535/51669888986_03d21ff75d_o.gif",
    "link_bin": "https://github.com/lmbstudiocontact/mb6_1/raw/main/2357.bin",
    "id_bin": "2357",
    "list_language": [],
    "array_tags": [
      "game",
      "anime"
    ],
    "list_album": [
      {
        "id_album": "63410260",
        "link_thumb": "https://live.staticflickr.com/65535/51669888986_03d21ff75d_o.gif",
        "title": "Anime"
      }
    ]
  },
  {
    "author": "nutchakrit",
    "link_thumb": "https://live.staticflickr.com/65535/51668853527_70bf9bd0e9_o.gif",
    "link_bin": "https://github.com/lmbstudiocontact/mb6_1/raw/main/2358.bin",
    "id_bin": "2358",
    "list_language": [],
    "array_tags": [
      "game",
      "anime"
    ],
    "list_album": [
      {
        "id_album": "63410260",
        "link_thumb": "https://live.staticflickr.com/65535/51668853527_70bf9bd0e9_o.gif",
        "title": "Anime"
      }
    ]
  },
  {
    "author": "nutchakrit",
    "link_thumb": "https://live.staticflickr.com/65535/51670338174_0b2ba451ba_o.gif",
    "link_bin": "https://github.com/lmbstudiocontact/mb6_1/raw/main/2359.bin",
    "id_bin": "2359",
    "list_language": [],
    "array_tags": [
      "game",
      "anime"
    ],
    "list_album": [
      {
        "id_album": "63410260",
        "link_thumb": "https://live.staticflickr.com/65535/51670338174_0b2ba451ba_o.gif",
        "title": "Anime"
      }
    ]
  }
]