[
  {
    "author": "cvg8",
    "link_thumb": "https://live.staticflickr.com/65535/51788227220_d7f1afa1d3_o.gif",
    "link_bin": "https://github.com/lmbstudiocontact/mb6_0/raw/main/100.bin",
    "id_bin": "100",
    "list_language": [],
    "array_tags": [
      "colors"
    ],
    "list_album": [
      {
        "id_album": "2433880",
        "link_thumb": "https://live.staticflickr.com/65535/51788227220_d7f1afa1d3_o.gif",
        "title": "None"
      }
    ]
  },
  {
    "author": "mpsspencer",
    "link_thumb": "https://live.staticflickr.com/65535/51787969424_bc4d8d24ac_o.gif",
    "link_bin": "https://github.com/lmbstudiocontact/mb6_0/raw/main/1118.bin",
    "id_bin": "1118",
    "list_language": [],
    "array_tags": [
      "bluetooth",
      "notdisturb",
      "lock",
      "time",
      "battery",
      "sport",
      "colors"
    ],
    "list_album": [
      {
        "id_album": "2433880",
        "link_thumb": "https://live.staticflickr.com/65535/51787969424_bc4d8d24ac_o.gif",
        "title": "None"
      }
    ]
  },
  {
    "author": "mpsspencer",
    "link_thumb": "https://live.staticflickr.com/65535/51788214235_84f1bb1cd8_o.gif",
    "link_bin": "https://github.com/lmbstudiocontact/mb6_0/raw/main/1232.bin",
    "id_bin": "1232",
    "list_language": [],
    "array_tags": [
      "red",
      "blue",
      "time",
      "colors"
    ],
    "list_album": [
      {
        "id_album": "2433880",
        "link_thumb": "https://live.staticflickr.com/65535/51788214235_84f1bb1cd8_o.gif",
        "title": "None"
      }
    ]
  },
  {
    "author": "RyoLumea",
    "link_thumb": "https://live.staticflickr.com/65535/51787348306_cfbb6c3786_o.gif",
    "link_bin": "https://github.com/lmbstudiocontact/mb6_0/raw/main/315.bin",
    "id_bin": "315",
    "list_language": [],
    "array_tags": [
      "basic",
      "colors"
    ],
    "list_album": [
      {
        "id_album": "2433880",
        "link_thumb": "https://live.staticflickr.com/65535/51787348306_cfbb6c3786_o.gif",
        "title": "None"
      }
    ]
  },
  {
    "author": "RyoLumea",
    "link_thumb": "https://live.staticflickr.com/65535/51787972534_2d4b148798_o.gif",
    "link_bin": "https://github.com/lmbstudiocontact/mb6_0/raw/main/316.bin",
    "id_bin": "316",
    "list_language": [],
    "array_tags": [
      "simple",
      "basic",
      "colors"
    ],
    "list_album": [
      {
        "id_album": "2433880",
        "link_thumb": "https://live.staticflickr.com/65535/51787972534_2d4b148798_o.gif",
        "title": "None"
      }
    ]
  },
  {
    "author": "RyoLumea",
    "link_thumb": "https://live.staticflickr.com/65535/51788220460_19f69d720c_o.gif",
    "link_bin": "https://github.com/lmbstudiocontact/mb6_0/raw/main/318.bin",
    "id_bin": "318",
    "list_language": [],
    "array_tags": [
      "white",
      "black",
      "simple",
      "basic",
      "colors"
    ],
    "list_album": [
      {
        "id_album": "2433880",
        "link_thumb": "https://live.staticflickr.com/65535/51788220460_19f69d720c_o.gif",
        "title": "None"
      }
    ]
  },
  {
    "author": "magnim",
    "link_thumb": "https://live.staticflickr.com/65535/51787958579_97a95d2b79_o.gif",
    "link_bin": "https://github.com/lmbstudiocontact/mb6_0/raw/main/618.bin",
    "id_bin": "618",
    "list_language": [],
    "array_tags": [
      "digital",
      "miband6",
      "weather",
      "pulse",
      "calories",
      "steps",
      "colors"
    ],
    "list_album": [
      {
        "id_album": "2433880",
        "link_thumb": "https://live.staticflickr.com/65535/51787958579_97a95d2b79_o.gif",
        "title": "None"
      }
    ]
  },
  {
    "author": "magnim",
    "link_thumb": "https://live.staticflickr.com/65535/51786515522_dc12a42218_o.gif",
    "link_bin": "https://github.com/lmbstudiocontact/mb6_0/raw/main/665.bin",
    "id_bin": "665",
    "list_language": [],
    "array_tags": [
      "digital",
      "miband6",
      "distance",
      "weather",
      "pulse",
      "calories",
      "steps",
      "colors"
    ],
    "list_album": [
      {
        "id_album": "2433880",
        "link_thumb": "https://live.staticflickr.com/65535/51786515522_dc12a42218_o.gif",
        "title": "None"
      }
    ]
  },
  {
    "author": "magnim",
    "link_thumb": "https://live.staticflickr.com/65535/51787956154_b89aba9d37_o.gif",
    "link_bin": "https://github.com/lmbstudiocontact/mb6_0/raw/main/690.bin",
    "id_bin": "690",
    "list_language": [],
    "array_tags": [
      "digital",
      "miband6",
      "distance",
      "pulse",
      "weather",
      "calories",
      "steps",
      "colors"
    ],
    "list_album": [
      {
        "id_album": "2433880",
        "link_thumb": "https://live.staticflickr.com/65535/51787956154_b89aba9d37_o.gif",
        "title": "None"
      }
    ]
  },
  {
    "author": "magnim",
    "link_thumb": "https://live.staticflickr.com/65535/51787575003_fa5f99a48c_o.gif",
    "link_bin": "https://github.com/lmbstudiocontact/mb6_0/raw/main/836.bin",
    "id_bin": "836",
    "list_language": [],
    "array_tags": [
      "digital",
      "miband6",
      "english",
      "pulse",
      "weather",
      "calories",
      "colors"
    ],
    "list_album": [
      {
        "id_album": "2433880",
        "link_thumb": "https://live.staticflickr.com/65535/51787575003_fa5f99a48c_o.gif",
        "title": "None"
      }
    ]
  },
  {
    "author": "Samwinder_BR",
    "link_thumb": "https://live.staticflickr.com/65535/51787572453_2ef2566340_o.gif",
    "link_bin": "https://github.com/lmbstudiocontact/mb6_0/raw/main/907.bin",
    "id_bin": "907",
    "list_language": [],
    "array_tags": [
      "brasil",
      "simple",
      "colors"
    ],
    "list_album": [
      {
        "id_album": "2433880",
        "link_thumb": "https://live.staticflickr.com/65535/51787572453_2ef2566340_o.gif",
        "title": "None"
      }
    ]
  },
  {
    "author": "joeddson",
    "link_thumb": "https://live.staticflickr.com/65535/51786500767_9b5687dc53_o.gif",
    "link_bin": "https://github.com/lmbstudiocontact/mb6_1/raw/main/2402.bin",
    "id_bin": "2402",
    "list_language": [],
    "array_tags": [
      "digital",
      "bignumbers",
      "date",
      "apple",
      "minimal",
      "pulse",
      "battery",
      "steps",
      "colors",
      "watchos"
    ],
    "list_album": [
      {
        "id_album": "2433880",
        "link_thumb": "https://live.staticflickr.com/65535/51786500767_9b5687dc53_o.gif",
        "title": "None"
      }
    ]
  },
  {
    "author": "ahmadjie80",
    "link_thumb": "https://live.staticflickr.com/65535/51787942099_3b28b93032_o.gif",
    "link_bin": "https://github.com/lmbstudiocontact/mb6_1/raw/main/2408.bin",
    "id_bin": "2408",
    "list_language": [],
    "array_tags": [
      "digital",
      "date",
      "weekday",
      "calories",
      "battery",
      "steps",
      "colors",
      "bluetooth",
      "stepprogress",
      "weather",
      "pulse",
      "lock",
      "dnd"
    ],
    "list_album": [
      {
        "id_album": "2433880",
        "link_thumb": "https://live.staticflickr.com/65535/51787942099_3b28b93032_o.gif",
        "title": "None"
      }
    ]
  }
]