[
  {
    "author": "cvg8",
    "link_thumb": "https://live.staticflickr.com/65535/51669819706_0c519641d9_o.gif",
    "link_bin": "https://github.com/lmbstudiocontact/mb6_1/raw/main/98.bin",
    "id_bin": "98",
    "list_language": [],
    "array_tags": [
      "green",
      "celta",
      "celtic",
      "verde",
      "irlanda",
      "galicia"
    ],
    "list_album": [
      {
        "id_album": "2433880",
        "link_thumb": "https://live.staticflickr.com/65535/51669819706_0c519641d9_o.gif",
        "title": "None"
      }
    ]
  }
]